streamlit_gettext/__init__.py
streamlit_gettext/streamlit_gettext.py
streamlit_gettext-0.0.4.dist-info/LICENSE
streamlit_gettext-0.0.4.dist-info/METADATA
streamlit_gettext-0.0.4.dist-info/WHEEL
streamlit_gettext-0.0.4.dist-info/top_level.txt
streamlit_gettext-0.0.4.dist-info/RECORD
