Metadata-Version: 2.2
Name: streamlit-gettext
Version: 0.0.4
Summary: A Streamlit extension for easy localization of your apps
Author-email: insolor <insolor@gmail.com>
Project-URL: homepage, https://github.com/insolor/streamlit-gettext
Project-URL: repository, https://github.com/insolor/streamlit-gettext
Keywords: streamlit,gettext,i18n
Classifier: License :: OSI Approved :: MIT License
Classifier: Development Status :: 3 - Alpha
Classifier: Operating System :: OS Independent
Classifier: License :: OSI Approved :: MIT License
Classifier: Programming Language :: Python
Classifier: Programming Language :: Python :: 3
Classifier: Programming Language :: Python :: 3.9
Classifier: Programming Language :: Python :: 3.10
Classifier: Programming Language :: Python :: 3.11
Classifier: Programming Language :: Python :: 3.12
Classifier: Programming Language :: Python :: 3.13
Classifier: Intended Audience :: Developers
Classifier: Topic :: Software Development :: Libraries :: Python Modules
Requires-Python: >=3.9
License-File: LICENSE
Requires-Dist: streamlit<2.0.0,>=1.37.0
